smartscheduler/__init__.py
smartscheduler/master_machine/__init__.py
smartscheduler/master_machine/co2_model.py
smartscheduler/master_machine/compute/README.md
smartscheduler/master_machine/compute/client_library/README.md
smartscheduler/master_machine/compute/client_library/__init__.py
smartscheduler/master_machine/compute/client_library/ingredients/__init__.py
smartscheduler/master_machine/compute/client_library/ingredients/disks/attach_disk.py
smartscheduler/master_machine/compute/client_library/ingredients/disks/autodelete_change.py
smartscheduler/master_machine/compute/client_library/ingredients/disks/clone_encrypted_disk.py
smartscheduler/master_machine/compute/client_library/ingredients/disks/clone_encrypted_disk_managed_key.py
smartscheduler/master_machine/compute/client_library/ingredients/disks/create_empty_disk.py
smartscheduler/master_machine/compute/client_library/ingredients/disks/create_from_image.py
smartscheduler/master_machine/compute/client_library/ingredients/disks/create_from_snapshot.py
smartscheduler/master_machine/compute/client_library/ingredients/disks/create_from_source.py
smartscheduler/master_machine/compute/client_library/ingredients/disks/create_kms_encrypted_disk.py
smartscheduler/master_machine/compute/client_library/ingredients/disks/delete.py
smartscheduler/master_machine/compute/client_library/ingredients/disks/disk_from_snapshot.py
smartscheduler/master_machine/compute/client_library/ingredients/disks/empty_disk.py
smartscheduler/master_machine/compute/client_library/ingredients/disks/from_image.py
smartscheduler/master_machine/compute/client_library/ingredients/disks/get.py
smartscheduler/master_machine/compute/client_library/ingredients/disks/list.py
smartscheduler/master_machine/compute/client_library/ingredients/disks/local_ssd.py
smartscheduler/master_machine/compute/client_library/ingredients/disks/regional_create_from_source.py
smartscheduler/master_machine/compute/client_library/ingredients/disks/regional_delete.py
smartscheduler-0.0.4.dist-info/LICENSE
smartscheduler-0.0.4.dist-info/METADATA
smartscheduler-0.0.4.dist-info/WHEEL
smartscheduler-0.0.4.dist-info/RECORD
